webservices/__init__.py
webservices/async.py
webservices/exceptions.py
webservices/models.py
webservices/sync.py
webservices/tests.py
webservices-0.6.dist-info/DESCRIPTION.rst
webservices-0.6.dist-info/METADATA
webservices-0.6.dist-info/metadata.json
webservices-0.6.dist-info/RECORD
webservices-0.6.dist-info/top_level.txt
webservices-0.6.dist-info/WHEEL
