Metadata-Version: 2.0
Name: webservices
Version: 0.6
Summary: UNKNOWN
Home-page: UNKNOWN
Author: Jonas Obrist
Author-email: UNKNOWN
License: BSD License
Platform: OS Independent
Requires-Dist: itsdangerous
Provides-Extra: consumer
Requires-Dist: requests; extra == 'consumer'
Provides-Extra: django
Requires-Dist: django (<1.7); extra == 'django'
Requires-Dist: requests; extra == 'django'
Provides-Extra: flask
Requires-Dist: flask; extra == 'flask'
Requires-Dist: requests; extra == 'flask'
Provides-Extra: twisted
Requires-Dist: twisted; extra == 'twisted'
